express/__init__.py
express/helpers.py
express/request.py
express/response.py
express/router.py
web_express_py-0.0.10.dist-info/METADATA
web_express_py-0.0.10.dist-info/WHEEL
web_express_py-0.0.10.dist-info/licenses/LICENSE
web_express_py-0.0.10.dist-info/RECORD
