Metadata-Version: 2.1
Name: web_express_py
Version: 0.0.10
Summary: Webserver written as express.js
Project-URL: Source Code, https://github.com/Hattorius/express.py
Project-URL: Issues, https://github.com/Hattorius/express.py/issues
Project-URL: Wiki, https://github.com/Hattorius/express.py/wiki
Author-email: Aaron <AJ@jonk.name>
License-File: LICENSE
Requires-Python: >=3.7
